getpaper/__init__.py
getpaper/download.py
getpaper/parse.py
getpaper/selenium_download.py
getpaper/test.py
getpaper-0.5.0.dist-info/LICENSE
getpaper-0.5.0.dist-info/METADATA
getpaper-0.5.0.dist-info/WHEEL
getpaper-0.5.0.dist-info/entry_points.txt
getpaper-0.5.0.dist-info/top_level.txt
getpaper-0.5.0.dist-info/RECORD
