Metadata-Version: 2.1
Name: getpaper
Version: 0.5.0
Summary: getpaper - papers download made easy!
Author: antonkulaga (Anton Kulaga)
Author-email: <antonkulaga@gmail.com>
Keywords: python,utils,files,papers,download
Classifier: Development Status :: 2 - Pre-Alpha
Classifier: Intended Audience :: Developers
Classifier: Programming Language :: Python :: 3.10
Classifier: Programming Language :: Python :: 3.11
Classifier: Operating System :: Unix
Classifier: Operating System :: MacOS :: MacOS X
Classifier: Operating System :: Microsoft :: Windows
License-File: LICENSE
Requires-Dist: pycomfort >=0.0.15
Requires-Dist: click
Requires-Dist: pynction
Requires-Dist: langchain >=0.2.1
Requires-Dist: langchain-community >=0.2.1
Requires-Dist: scidownl >=1.0.2
Requires-Dist: semanticscholar >=0.8.1
Requires-Dist: Deprecated
Requires-Dist: PyMuPDF >=1.24.4
Requires-Dist: unpywall >=0.2.3
Requires-Dist: nest-asyncio >=1.6.0
Requires-Dist: chardet
Requires-Dist: transformers
Provides-Extra: plumber
Requires-Dist: pdfplumber >=0.10.3 ; extra == 'plumber'
Provides-Extra: selenium
Requires-Dist: selenium ; extra == 'selenium'
Requires-Dist: webdriver-manager ; extra == 'selenium'
Provides-Extra: unstructured
Requires-Dist: pdfminer.six ; extra == 'unstructured'
Requires-Dist: unstructured >=0.10.25 ; extra == 'unstructured'
Requires-Dist: unstructured-inference >=0.7.21 ; extra == 'unstructured'
Requires-Dist: unstructured[local-inference] ; extra == 'unstructured'
Requires-Dist: unstructured.PaddleOCR >=2.6.1.3 ; extra == 'unstructured'
